spdx3_validate/__init__.py
spdx3_validate/__main__.py
spdx3_validate/main.py
spdx3_validate/spdx_versions.py
spdx3_validate/version.py
spdx3_validate-0.0.5.dist-info/METADATA
spdx3_validate-0.0.5.dist-info/WHEEL
spdx3_validate-0.0.5.dist-info/entry_points.txt
spdx3_validate-0.0.5.dist-info/licenses/LICENSE
spdx3_validate-0.0.5.dist-info/RECORD
