Metadata-Version: 2.3
Name: spdx3-validate
Version: 0.0.5
Summary: Validates SPDX 3 data files
Project-URL: Homepage, https://github.com/JPEWdev/spdx3-validate
Project-URL: Repository, https://github.com/JPEWdev/spdx3-validate.git
Project-URL: Issues, https://github.com/JPEWdev/spdx3-validate/issues
Author-email: Joshua Watt <JPEWhacker@gmail.com>
Classifier: Development Status :: 4 - Beta
Classifier: Intended Audience :: Developers
Classifier: License :: OSI Approved :: MIT License
Classifier: Programming Language :: Python :: 3
Classifier: Programming Language :: Python :: 3.8
Classifier: Programming Language :: Python :: 3.9
Classifier: Programming Language :: Python :: 3.10
Classifier: Programming Language :: Python :: 3.11
Classifier: Programming Language :: Python :: 3.12
Classifier: Topic :: Software Development :: Build Tools
Requires-Python: >=3.8
Requires-Dist: halo>=0.0.31
Requires-Dist: jsonschema>=4.21.1
Requires-Dist: pyshacl>=0.25.0
Requires-Dist: rdflib>=7.0.0
Provides-Extra: dev
Requires-Dist: flake8>=7.0.0; extra == 'dev'
Requires-Dist: pytest-cov>=4.1; extra == 'dev'
Requires-Dist: pytest>=7.4; extra == 'dev'
